tgpdc_mailer/__init__.py
tgpdc_mailer/mailer.py
tgpdc_mailer-0.1.2.dist-info/METADATA
tgpdc_mailer-0.1.2.dist-info/WHEEL
tgpdc_mailer-0.1.2.dist-info/licenses/LICENSE
tgpdc_mailer-0.1.2.dist-info/RECORD
