Metadata-Version: 2.4
Name: tgpdc-mailer
Version: 0.1.2
Summary: A simple package for sending templated emails using Microsoft Graph API
Author-email: Simphiwe Yende <simphiwe.yende@tgpdc.com>
License-File: LICENSE
Classifier: License :: OSI Approved :: MIT License
Classifier: Operating System :: OS Independent
Classifier: Programming Language :: Python :: 3
Requires-Python: >=3.7
Requires-Dist: python-dotenv>=0.19.0
Requires-Dist: requests>=2.28.0
